plasmapy/README.md
plasmapy/__init__.py
plasmapy/_version.py
plasmapy/py.typed
plasmapy/analysis/__init__.py
plasmapy/analysis/fit_functions.py
plasmapy/analysis/nullpoint.py
plasmapy/analysis/swept_langmuir/__init__.py
plasmapy/analysis/swept_langmuir/floating_potential.py
plasmapy/analysis/swept_langmuir/helpers.py
plasmapy/analysis/swept_langmuir/ion_saturation_current.py
plasmapy/analysis/time_series/__init__.py
plasmapy/analysis/time_series/conditional_averaging.py
plasmapy/analysis/time_series/excess_statistics.py
plasmapy/analysis/time_series/running_moments.py
plasmapy/diagnostics/__init__.py
plasmapy/diagnostics/langmuir.py
plasmapy/diagnostics/thomson.py
plasmapy/diagnostics/charged_particle_radiography/__init__.py
plasmapy/diagnostics/charged_particle_radiography/detector_stacks.py
plasmapy/diagnostics/charged_particle_radiography/synthetic_radiography.py
plasmapy/diagnostics/swept_langmuir/__init__.py
plasmapy/dispersion/__init__.py
plasmapy/dispersion/dispersion_functions.py
plasmapy/dispersion/analytical/__init__.py
plasmapy/dispersion/analytical/mhd_waves_.py
plasmapy/dispersion/analytical/stix_.py
plasmapy/dispersion/analytical/two_fluid_.py
plasmapy/dispersion/numerical/__init__.py
plasmapy/dispersion/numerical/hollweg_.py
plasmapy/dispersion/numerical/kinetic_alfven_.py
plasmapy/formulary/__init__.py
plasmapy/formulary/braginskii.py
plasmapy/formulary/densities.py
plasmapy/formulary/dielectric.py
plasmapy/formulary/dimensionless.py
plasmapy/formulary/distribution.py
plasmapy/formulary/drifts.py
plasmapy/formulary/frequencies.py
plasmapy/formulary/ionization.py
plasmapy/formulary/laser.py
plasmapy/formulary/lengths.py
plasmapy/formulary/magnetostatics.py
plasmapy/formulary/mathematics.py
plasmapy/formulary/misc.py
plasmapy/formulary/quantum.py
plasmapy/formulary/radiation.py
plasmapy/formulary/relativity.py
plasmapy/formulary/speeds.py
plasmapy/formulary/collisions/__init__.py
plasmapy/formulary/collisions/coulomb.py
plasmapy-2025.10.0.dist-info/licenses/LICENSE.md
plasmapy-2025.10.0.dist-info/METADATA
plasmapy-2025.10.0.dist-info/WHEEL
plasmapy-2025.10.0.dist-info/entry_points.txt
plasmapy-2025.10.0.dist-info/top_level.txt
plasmapy-2025.10.0.dist-info/RECORD
