Metadata-Version: 2.4
Name: plasmapy
Version: 2025.10.0
Summary: Python package for plasma science
Project-URL: Changelog, https://docs.plasmapy.org/en/stable/whatsnew/index.html
Project-URL: Chat, https://plasmapy.org/chat
Project-URL: Documentation, https://docs.plasmapy.org/
Project-URL: Issues, https://github.com/PlasmaPy/plasmapy/issues/
Project-URL: Source, https://github.com/PlasmaPy/plasmapy
Project-URL: website, https://www.plasmapy.org
Keywords: astronomy,fusion,heliophysics,plasma,plasma physics,science,solar physics,space plasmas
Classifier: Intended Audience :: Education
Classifier: Intended Audience :: Science/Research
Classifier: Natural Language :: English
Classifier: Operating System :: OS Independent
Classifier: Programming Language :: Python :: 3 :: Only
Classifier: Programming Language :: Python :: 3.12
Classifier: Programming Language :: Python :: 3.13
Classifier: Programming Language :: Python :: 3.14
Classifier: Topic :: Scientific/Engineering :: Astronomy
Classifier: Topic :: Scientific/Engineering :: Physics
Requires-Python: >=3.12
License-File: LICENSE.md
Requires-Dist: astropy>=6
Requires-Dist: h5py>=3.11
Requires-Dist: lmfit>=1.3
Requires-Dist: matplotlib>=3.8
Requires-Dist: mpmath>=1.3
Requires-Dist: numpy>=1.26
Requires-Dist: packaging>=24
Requires-Dist: pandas>=2.1.4
Requires-Dist: requests>=2.30
Requires-Dist: scipy>=1.11
Requires-Dist: tqdm>=4.65
Requires-Dist: wrapt>=1.15
Requires-Dist: xarray>=2024.5
Provides-Extra: docs
Requires-Dist: docutils>=0.21.2; extra == "docs"
Requires-Dist: ipykernel>=7.0.1; extra == "docs"
Requires-Dist: ipywidgets>=8.1.7; extra == "docs"
Requires-Dist: jinja2>=3.1.6; extra == "docs"
Requires-Dist: nbsphinx>=0.9.6; extra == "docs"
Requires-Dist: nox[uv]>=2025.10.16; extra == "docs"
Requires-Dist: numpydoc>=1.9; extra == "docs"
Requires-Dist: pillow>=12; extra == "docs"
Requires-Dist: plasmapy-sphinx>=2025.5.1; extra == "docs"
Requires-Dist: pygments==2.19.2; extra == "docs"
Requires-Dist: sphinx<8.3,>=8.2.3; extra == "docs"
Requires-Dist: sphinx-changelog>=1.6; extra == "docs"
Requires-Dist: sphinx-codeautolink==0.17.5; extra == "docs"
Requires-Dist: sphinx-collapse>=0.1.3; extra == "docs"
Requires-Dist: sphinx-copybutton>=0.5.2; extra == "docs"
Requires-Dist: sphinx-gallery>=0.19; extra == "docs"
Requires-Dist: sphinx-issues>=5.0.1; extra == "docs"
Requires-Dist: sphinx-notfound-page>=1.1; extra == "docs"
Requires-Dist: sphinx-reredirects>=1; extra == "docs"
Requires-Dist: sphinx-rtd-theme>=3.0.2; extra == "docs"
Requires-Dist: sphinx-tabs>=3.4.7; extra == "docs"
Requires-Dist: sphinxcontrib-bibtex>=2.6.5; extra == "docs"
Requires-Dist: sphinxcontrib-globalsubs>=0.1.2; extra == "docs"
Requires-Dist: sphinxemoji>=0.3.1; extra == "docs"
Requires-Dist: towncrier>=24.8; extra == "docs"
Requires-Dist: unidecode>=1.4; extra == "docs"
Provides-Extra: tests
Requires-Dist: hypothesis>=6.142.3; extra == "tests"
Requires-Dist: mypy>=1.18.2; extra == "tests"
Requires-Dist: nox[uv]>=2025.10.16; extra == "tests"
Requires-Dist: pytest>=8.4.2; extra == "tests"
Requires-Dist: pytest-cov>=7; extra == "tests"
Requires-Dist: pytest-filter-subpackage>=0.2; extra == "tests"
Requires-Dist: pytest-regressions>=2.8.3; extra == "tests"
Requires-Dist: pytest-rerunfailures>=16.1; extra == "tests"
Requires-Dist: pytest-xdist>=3.8; extra == "tests"
Dynamic: license-file
